pipsetup/__init__.py
pipsetup/generator.py
pipsetup/progress/color_text.py
pipsetup/progress/progress.py
pipsetup/templates/__init__.py
pipsetup/templates/file_project_template.py
pipsetup/templates/manifest_template.in
pipsetup/templates/publish_yml_template.yml
pipsetup/templates/readme_template.md
pipsetup/templates/setup_cfg_template.cfg
pipsetup/templates/setup_py_template.py
pipsetup-0.2.dist-info/METADATA
pipsetup-0.2.dist-info/WHEEL
pipsetup-0.2.dist-info/entry_points.txt
pipsetup-0.2.dist-info/top_level.txt
pipsetup-0.2.dist-info/RECORD
