Metadata-Version: 2.1
Name: pipsetup
Version: 0.2
Summary: A tool to generate Python project structures
Home-page: https://github.com/leonardogonzalolaura/workspace_setup_pip
Author: Leonardo Daniel Gonzalo Laura
Author-email: glleonardodaniel@gmail.com
Classifier: Programming Language :: Python :: 3
Classifier: License :: OSI Approved :: MIT License
Classifier: Operating System :: OS Independent
Requires-Python: >=3.6
